Metadata-Version: 2.1
Name: pygitt
Version: 0.0.3
Summary: A module in pip where you can use git commands
Home-page: UNKNOWN
Author: Mohammed Daniyal
Author-email: danides450@gmail.com
License: MIT
Keywords: git
Platform: UNKNOWN
Classifier: Development Status :: 5 - Production/Stable
Classifier: Intended Audience :: Education
Classifier: Operating System :: Microsoft :: Windows :: Windows 10
Classifier: License :: OSI Approved :: MIT License
Classifier: Programming Language :: Python :: 3
